survivalPredictor
