Metadata-Version: 1.1
Name: survivalPredictor
Version: 0.4
Summary: survivalPredictor for NORBIS Mini-challenge
Home-page: https://github.com/asntech/survivalPredictor
Author: Aziz Khan
Author-email: aziz.khan@ncmm.uio.no
License: UNKNOWN
Platform: UNKNOWN
Classifier: Intended Audience :: Developers
Classifier: Intended Audience :: Science/Research
Classifier: License :: OSI Approved :: MIT License
Classifier: Operating System :: OS Independent
Classifier: Programming Language :: Python :: 2.7
Classifier: Topic :: Scientific/Engineering :: Bio-Informatics
